setup.py
src/falcon_exceptions/__init__.py
src/falcon_exceptions/exceptions.py
src/falcon_exceptions.egg-info/PKG-INFO
src/falcon_exceptions.egg-info/SOURCES.txt
src/falcon_exceptions.egg-info/dependency_links.txt
src/falcon_exceptions.egg-info/requires.txt
src/falcon_exceptions.egg-info/top_level.txt