Metadata-Version: 1.0
Name: falcon-exceptions
Version: 0.1.0
Summary: Falcon Exceptions
Home-page: https://github.com/aschavez/falcon-exceptions
Author: Andres Chavez
Author-email: aschavezu@gmail.com
License: UNKNOWN
Keywords: falcon,exceptions
Platform: UNKNOWN
